mmdai_test/__init__.py
mmdai_test/print_str.py
mytest/__init__.py
mytest/print_str.py
mmdai_test-2.0.dist-info/LICENSE
mmdai_test-2.0.dist-info/METADATA
mmdai_test-2.0.dist-info/WHEEL
mmdai_test-2.0.dist-info/top_level.txt
mmdai_test-2.0.dist-info/RECORD
