Metadata-Version: 2.1
Name: mmdai-test
Version: 2.0
Summary: PyPI Tutorial
Author: mmdai
Author-email: mmdai@shu.edu.cn
Classifier: Programming Language :: Python :: 3
Classifier: License :: OSI Approved :: MIT License
Classifier: Operating System :: OS Independent
Requires-Python: >=3
License-File: LICENSE
Requires-Dist: pymysql (>=0.10.0)
Requires-Dist: openpyxl (>=3.0.5)
